{
  "_comment": "Alias -> release package name for VOICE_RELEASE_BASE_URL/<package>.tar.gz downloads. Package names match the directories under releases/multivoice-20260713 in the saanoTTS research repo, which is what tools/export_roota_self_contained_package.py produces per voice.",
  "voices": {
    "amy": { "package": "amy-en-1p46m", "language": "en_US", "sample_rate": 22050 },
    "amy-1p1m": { "package": "amy-en-1p1m", "language": "en_US", "sample_rate": 22050 },
    "amy-1p8m": { "package": "amy-en-1p8m", "language": "en_US", "sample_rate": 22050 },
    "hfc": { "package": "hfc-en-1p8m", "language": "en_US", "sample_rate": 22050 },
    "kristin": { "package": "kristin-en-1p4m", "language": "en_US", "sample_rate": 22050 },
    "vi": { "package": "vi-vais1000-1p46m", "language": "vi_VN", "sample_rate": 22050 },
    "id": { "package": "id-newstts-1p46m", "language": "id_ID", "sample_rate": 22050 }
  }
}
